Luci/__init__.py
Luci/cli.py
Luci/optimizer.py
Luci/Agents/__init__.py
Luci/Agents/agent.py
Luci/Agents/chain.py
Luci/Agents/chat_agent.py
Luci/Agents/medica_search_agent.py
Luci/Agents/search.py
Luci/Agents/soap.py
Luci/Agents/super_agent.py
Luci/Agents/voice_documentation_agent.py
Luci/Core/__init__.py
Luci/Core/medical_search.py
Luci/Core/search_image.py
Luci/Core/search_text.py
Luci/Models/__init__.py
Luci/Models/model.py
Luci/UI/__init__.py
Luci/Utils/__init__.py
Luci/Utils/agent_utils.py
Luci/Utils/gpt.py
Luci/Utils/rxnorm.py
Luci/Utils/transcribe.py
LuciAI-0.5.0.dist-info/LICENSE
LuciAI-0.5.0.dist-info/METADATA
LuciAI-0.5.0.dist-info/WHEEL
LuciAI-0.5.0.dist-info/entry_points.txt
LuciAI-0.5.0.dist-info/top_level.txt
LuciAI-0.5.0.dist-info/RECORD
