Metadata-Version: 2.1
Name: LuciAI
Version: 0.5.0
Summary: The First AI-Based Medical Agent Designed to Automate All Medical Processes.
Home-page: https://revmaxx.co
Author: wbavishek
Author-email: wbavishek@gmail.com
Classifier: Programming Language :: Python :: 3.8
Classifier: Operating System :: OS Independent
License-File: LICENSE
Requires-Dist: cerina
Requires-Dist: openai
Requires-Dist: together
Requires-Dist: langchain
Requires-Dist: langchain-together
Requires-Dist: langchain-core
Requires-Dist: langchain-community
Requires-Dist: ijson
Requires-Dist: pydantic
Requires-Dist: gradio
Requires-Dist: speechrecognition
Requires-Dist: biopython
Requires-Dist: pyyaml
